ezchlog/__init__.py
ezchlog/__main__.py
ezchlog/cli.py
ezchlog/config.py
ezchlog/ezchlog.py
ezchlog/py.typed
ezchlog-1.4.0.dist-info/licenses/LICENSE
ezchlog-1.4.0.dist-info/WHEEL
ezchlog-1.4.0.dist-info/entry_points.txt
ezchlog-1.4.0.dist-info/METADATA
ezchlog-1.4.0.dist-info/RECORD
