Metadata-Version: 2.4
Name: ezchlog
Version: 1.4.0
Summary: Easy git branch friendly changelogs
Keywords: changelog,release-notes,git,no-conflict,easy
Author: Cyrille Pontvieux
Author-email: Cyrille Pontvieux <cyrille@enialis.net>
License-Expression: MIT
License-File: LICENSE
Classifier: Development Status :: 5 - Production/Stable
Classifier: Intended Audience :: Developers
Classifier: Natural Language :: English
Classifier: Operating System :: OS Independent
Classifier: Environment :: Console
Classifier: License :: OSI Approved :: MIT License
Classifier: Programming Language :: Python :: 3.10
Classifier: Programming Language :: Python :: 3.11
Classifier: Programming Language :: Python :: 3.12
Classifier: Programming Language :: Python :: 3.13
Classifier: Programming Language :: Python :: 3.14
Classifier: Topic :: Documentation
Classifier: Topic :: Software Development :: Documentation
Classifier: Topic :: Text Processing :: Markup :: Markdown
Classifier: Typing :: Typed
Requires-Dist: tomli ; python_full_version < '3.11'
Requires-Python: >=3.10
Project-URL: Repository, https://gitlab.com/snake_coders/ezchlog
Project-URL: Documentation, https://gitlab.com/snake_coders/ezchlog/-/blob/master/README.md
Project-URL: Bug Tracker, https://gitlab.com/snake_coders/ezchlog/-/issues
Project-URL: Merge Requests, https://gitlab.com/snake_coders/ezchlog/-/merge_requests
Project-URL: Changelog, https://gitlab.com/snake_coders/ezchlog/-/blob/master/CHANGELOG.md
Project-URL: Contributing, https://gitlab.com/snake_coders/ezchlog/-/blob/master/CONTRIBUTING.md
